src/__init__.py
src/data/.gitkeep
src/data/__init__.py
src/data/make_dataset.py
src/features/.gitkeep
src/features/__init__.py
src/features/build_features.py
src/models/.gitkeep
src/models/__init__.py
src/models/predict_model.py
src/models/retrieve_fit_model.py
src/models/train/gradient_boosting/__init__.py
src/models/train/gradient_boosting/conda.yaml
src/models/train/gradient_boosting/gradient_boosting_train.py
src/models/train/gradient_boosting/MLproject
src/models/train/random_forest/__init__.py
src/models/train/random_forest/conda.yaml
src/models/train/random_forest/MLproject
src/models/train/random_forest/random_forest_train.py
src/models/train/xgboost/__init__.py
src/models/train/xgboost/conda.yaml
src/models/train/xgboost/MLproject
src/models/train/xgboost/xgboost_train.py
home_credit-1.1.2.dist-info/LICENSE
home_credit-1.1.2.dist-info/METADATA
home_credit-1.1.2.dist-info/WHEEL
home_credit-1.1.2.dist-info/RECORD
