Metadata-Version: 2.1
Name: home-credit
Version: 1.1.2
Summary: applications of big data project
License: MIT
Author: halmouch
Requires-Python: >=3.9,<3.10
Classifier: License :: OSI Approved :: MIT License
Classifier: Programming Language :: Python :: 3
Classifier: Programming Language :: Python :: 3.9
Requires-Dist: Sphinx (>=4.3.0,<5.0.0)
Requires-Dist: ipython (>=7.29.0,<8.0.0)
Requires-Dist: jupyter (>=1.0.0,<2.0.0)
Requires-Dist: kaggle (>=1.5.12,<2.0.0)
Requires-Dist: matplotlib (>=3.5.0,<4.0.0)
Requires-Dist: mlflow (>=1.21.0,<2.0.0)
Requires-Dist: nbsphinx (>=0.8.7,<0.9.0)
Requires-Dist: numba (>=0.54.1,<0.55.0)
Requires-Dist: numpy (==1.20.0)
Requires-Dist: pandas (>=1.3.4,<2.0.0)
Requires-Dist: requests (>=2.26.0,<3.0.0)
Requires-Dist: scikit-learn (>=1.0.1,<2.0.0)
Requires-Dist: urllib3 (>=1.26.7,<2.0.0)
Requires-Dist: xgboost (>=1.5.0,<2.0.0)
